sinaweibo_mcp_server-0.2.dist-info/licenses/LICENSE
test/__init__.py
test/post_weibo_via_mcpo.py
test/test_server.py
weibo_mcp_server/__init__.py
weibo_mcp_server/__login__.py
weibo_mcp_server/__main__.py
weibo_mcp_server/weibo_control.py
weibo_mcp_server/weibo_server.py
sinaweibo_mcp_server-0.2.dist-info/METADATA
sinaweibo_mcp_server-0.2.dist-info/WHEEL
sinaweibo_mcp_server-0.2.dist-info/entry_points.txt
sinaweibo_mcp_server-0.2.dist-info/top_level.txt
sinaweibo_mcp_server-0.2.dist-info/RECORD
