Metadata-Version: 2.4
Name: sinaweibo_mcp_server
Version: 0.2
Summary: weibo mcp server
Home-page: 
Author: MengAlong
Author-email: alongmeng@gmail.com
License: Apache2.0
Requires-Python: >=3.12
License-File: LICENSE
Requires-Dist: requests
Dynamic: author
Dynamic: author-email
Dynamic: description
Dynamic: description-content-type
Dynamic: license
Dynamic: license-file
Dynamic: requires-dist
Dynamic: requires-python
Dynamic: summary
